cron_times/__init__.py
cron_times/app.py
cron_times/db.py
cron_times/jobdef.py
cron_times/logging.py
cron_times/readers/__init__.py
cron_times/readers/argo_workflow.py
cron_times/readers/dbt_cloud.py
cron_times/static/css/bootstrap-icons.min.css
cron_times/static/css/bootstrap.min.css
cron_times/static/css/bootstrap.min.css.map
cron_times/static/css/fonts/bootstrap-icons.woff
cron_times/static/css/fonts/bootstrap-icons.woff2
cron_times/static/js/bootstrap.bundle.min.js
cron_times/static/js/bootstrap.bundle.min.js.map
cron_times/static/js/htmx-1.9.8.min.js
cron_times/templates/home.html
cron_times/templates/navbar.html
cron_times/templates/plan-item-now.html
cron_times/templates/plan-item.html
cron_times/templates/scripts.html
cron_times/templates/timezone-item.html
cron_times/templates/timezone-modal.html
cron_times-0.9.0.dist-info/LICENSE
cron_times-0.9.0.dist-info/METADATA
cron_times-0.9.0.dist-info/WHEEL
cron_times-0.9.0.dist-info/RECORD
