Metadata-Version: 2.1
Name: cron-times
Version: 0.9.0
Summary: Timetable for your cronjobs
License: Apache-2.0
Author: Tzu-Ting
Author-email: tzingshih@gmail.com
Requires-Python: >=3.11,<4.0
Classifier: License :: OSI Approved :: Apache Software License
Classifier: Programming Language :: Python :: 3
Classifier: Programming Language :: Python :: 3.11
Classifier: Programming Language :: Python :: 3.12
Requires-Dist: croniter (>=2.0.1,<3.0.0)
Requires-Dist: flask (>=3.0.0,<4.0.0)
Requires-Dist: humanize (>=4.9.0,<5.0.0)
Requires-Dist: mistune (>=3.0.2,<4.0.0)
Requires-Dist: pydantic (>=2.5.1,<3.0.0)
Requires-Dist: rapidfuzz (>=3.5.2,<4.0.0)
Requires-Dist: tomlkit (>=0.12.3,<0.13.0)
